{
  "customers": [
    {
      "id": 9,
      "name": "Nickie Frascone",
      "email": "nfrascone8@tinypic.com",
      "password": "pT9_9=#l$P=0"
    },
    {
      "id": 10,
      "name": "Minetta Metcalf",
      "email": "mmetcalf9@devhub.com",
      "password": "hB1`5%awg}D*A<Ga"
    },
    {
      "id": 11,
      "name": "Marget Treadger",
      "email": "mtreadgera@squarespace.com",
      "password": "iX4\"9{Z)8Ndg"
    },
    {
      "id": 12,
      "name": "Elfreda Todarini",
      "email": "etodarinib@ft.com",
      "password": "rP3!!?xHi<"
    },
    {
      "id": 13,
      "name": "Anne-corinne Lumsdall",
      "email": "alumsdallc@state.gov",
      "password": "eX4*GDt?y1viVKz6"
    },
    {
      "id": 14,
      "name": "Katinka Schelle",
      "email": "kschelled@mail.ru",
      "password": "wU9,TGm6BW7mO2xW"
    },
    {
      "id": 15,
      "name": "April Daniello",
      "email": "adanielloe@cmu.edu",
      "password": "bZ2=+\"m6N"
    },
    {
      "id": 16,
      "name": "Ruben Bowes",
      "email": "rbowesf@webmd.com",
      "password": "yQ5_RU>@uIo"
    },
    {
      "id": 17,
      "name": "Sascha Reames",
      "email": "sreamesg@seattletimes.com",
      "password": "gY0$j&/uGNZXGil"
    },
    {
      "id": 18,
      "name": "Thorn Poacher",
      "email": "tpoacherh@netscape.com",
      "password": "tJ5`Xu){d*}"
    },
    {
      "id": 19,
      "name": "Mata Schohier",
      "email": "mschohieri@icq.com",
      "password": "nL4{TEnz\\bLnfMQ"
    },
    {
      "id": 20,
      "name": "Mohandis Benedite",
      "email": "mbeneditej@dailymail.co.uk",
      "password": "nH6'fiCN/vO4+8?"
    },
    {
      "id": 21,
      "name": "Francoise Cranefield",
      "email": "fcranefieldk@blinklist.com",
      "password": "tE0!i\"N~"
    },
    {
      "id": 22,
      "name": "Juana Elvidge",
      "email": "jelvidgel@comsenz.com",
      "password": "vZ3=<#z)'>4*6/!"
    },
    {
      "id": 23,
      "name": "Barthel Jobbins",
      "email": "bjobbinsm@mac.com",
      "password": "xK3+?C(fZ/C|#%O"
    },
    {
      "id": 24,
      "name": "Leighton McFadin",
      "email": "lmcfadinn@indiatimes.com",
      "password": "gS0(nUaF=QIyQ~U"
    },
    {
      "id": 25,
      "name": "Vale Lince",
      "email": "vlinceo@sun.com",
      "password": "bZ0.Q>!*Q"
    },
    {
      "id": 26,
      "name": "Fredia Fawlo",
      "email": "ffawlop@skype.com",
      "password": "vM2(390X"
    },
    {
      "id": 27,
      "name": "Muffin Tremeer",
      "email": "mtremeerq@goo.gl",
      "password": "aM3@}j$gm8Ua<"
    },
    {
      "id": 29,
      "name": "Giacopo Kann",
      "email": "gkanns@twitpic.com",
      "password": "mQ6.2Ems*\"K"
    },
    {
      "id": 30,
      "name": "Jinny Havik",
      "email": "jhavikt@ihg.com",
      "password": "vG3.bL@,{6X@E"
    },
    {
      "id": 31,
      "name": "Jamill Adamovich",
      "email": "jadamovichu@jugem.jp",
      "password": "pK1@=/9(XY'o1Z"
    },
    {
      "id": 32,
      "name": "Ilaire Bertolaccini",
      "email": "ibertolacciniv@t.co",
      "password": "rI9|Za\\38Gq%.,_"
    },
    {
      "id": 33,
      "name": "Randy Chellam",
      "email": "rchellamw@tumblr.com",
      "password": "qR4?{T1WVmc/Rg"
    },
    {
      "id": 34,
      "name": "Min Teggart",
      "email": "mteggartx@discovery.com",
      "password": "xS0=.)n</E\\YB@sS"
    },
    {
      "id": 35,
      "name": "Margareta Woodroff",
      "email": "mwoodroffy@techcrunch.com",
      "password": "fG6+X!\\hY`RtiL."
    },
    {
      "id": 36,
      "name": "Fabio Benda",
      "email": "fbendaz@hhs.gov",
      "password": "qG4@E,rnk"
    },
    {
      "id": 37,
      "name": "Nealson Burness",
      "email": "nburness10@studiopress.com",
      "password": "lJ3\\_%US,<50p"
    },
    {
      "id": 38,
      "name": "Cookie Staves",
      "email": "cstaves11@nsw.gov.au",
      "password": "zH0(ZBgRb\\IKS\\E"
    },
    {
      "id": 39,
      "name": "Thaxter Gibbeson",
      "email": "tgibbeson12@redcross.org",
      "password": "vG8/)05MnND<>.)"
    },
    {
      "id": 40,
      "name": "Stesha Costanza",
      "email": "scostanza13@techcrunch.com",
      "password": "zF9$oK7`(z0GC"
    },
    {
      "id": 41,
      "name": "Hulda Christensen",
      "email": "hchristensen14@squidoo.com",
      "password": "jI1&T\"D=h"
    },
    {
      "id": 42,
      "name": "Ania Rouby",
      "email": "arouby15@webnode.com",
      "password": "xU2+s@H&)#"
    },
    {
      "id": 43,
      "name": "Elke Roof",
      "email": "eroof16@booking.com",
      "password": "eV5(x{K{~~`\\Rt"
    },
    {
      "id": 44,
      "name": "Elmo Hedde",
      "email": "ehedde17@independent.co.uk",
      "password": "tB3@I'rT\"0XcA1%"
    },
    {
      "id": 45,
      "name": "Angel Gauson",
      "email": "agauson18@tumblr.com",
      "password": "cK6/J2WZb'i'p_"
    },
    {
      "id": 46,
      "name": "Chilton Drinnan",
      "email": "cdrinnan19@usgs.gov",
      "password": "mZ5}UNJ$"
    },
    {
      "id": 47,
      "name": "Gordy Goulthorp",
      "email": "ggoulthorp1a@joomla.org",
      "password": "nL4=43qv7Xd="
    },
    {
      "id": 48,
      "name": "Daffy Skin",
      "email": "dskin1b@geocities.com",
      "password": "fP8/1CW/)i"
    },
    {
      "id": 49,
      "name": "Marlo Cicetti",
      "email": "mcicetti1c@sogou.com",
      "password": "rD9&!7<b/$)%U"
    },
    {
      "id": 50,
      "name": "Pascale Lewsam",
      "email": "plewsam1d@123-reg.co.uk",
      "password": "vE8%,Mk>H`u{~I17"
    },
    {
      "id": 51,
      "name": "Staford Hutten",
      "email": "shutten1e@freewebs.com",
      "password": "lF2=P5+D8/C07ge"
    },
    {
      "id": 52,
      "name": "Roxie Weller",
      "email": "rweller1f@shop-pro.jp",
      "password": "fY4{ig(MHwV5Ix&"
    },
    {
      "id": 53,
      "name": "Lockwood Chaston",
      "email": "lchaston1g@nifty.com",
      "password": "gH2\\va)N"
    },
    {
      "id": 54,
      "name": "Burr Grisbrook",
      "email": "bgrisbrook1h@paypal.com",
      "password": "oE7\"9xe=K4a"
    },
    {
      "id": 55,
      "name": "Diane-marie Adamowicz",
      "email": "dadamowicz1i@freewebs.com",
      "password": "qV5%K~aIvEVwnf+"
    },
    {
      "id": 56,
      "name": "Mimi Lancett",
      "email": "mlancett1j@epa.gov",
      "password": "nF3=~0+yD"
    },
    {
      "id": 57,
      "name": "Maible Ralfe",
      "email": "mralfe1k@bizjournals.com",
      "password": "hM1\\4qgR&o\\FmUFR"
    },
    {
      "id": 58,
      "name": "Krishnah Forster",
      "email": "kforster1l@marriott.com",
      "password": "dZ8%Ln(t=@rsr>"
    },
    {
      "id": 59,
      "name": "Omero Spain",
      "email": "ospain1m@yahoo.co.jp",
      "password": "uN6_gO#&C"
    },
    {
      "id": 60,
      "name": "Pammi Duprey",
      "email": "pduprey1n@de.vu",
      "password": "iQ5(O.V+=Z"
    },
    {
      "id": 61,
      "name": "Julee Poskitt",
      "email": "jposkitt1o@cbsnews.com",
      "password": "wR3`k5\\Ue"
    },
    {
      "id": 62,
      "name": "Cherrita Wisdish",
      "email": "cwisdish1p@slideshare.net",
      "password": "gY4#\"tk)"
    },
    {
      "id": 63,
      "name": "Camile Curnnokk",
      "email": "ccurnnokk1q@weibo.com",
      "password": "eT0#d&6f@bu"
    },
    {
      "id": 64,
      "name": "Nev Duddle",
      "email": "nduddle1r@moonfruit.com",
      "password": "qZ4!5r!_t@Z3}LR$"
    },
    {
      "id": 65,
      "name": "Waylon Kingerby",
      "email": "wkingerby1s@constantcontact.com",
      "password": "dR1=cxV_"
    },
    {
      "id": 66,
      "name": "Sheelah Allgood",
      "email": "sallgood1t@webmd.com",
      "password": "zQ3+9U_W!FFe9Jhz"
    },
    {
      "id": 67,
      "name": "Cortie Theobald",
      "email": "ctheobald1u@msu.edu",
      "password": "wZ0*3ULDVxh"
    },
    {
      "id": 68,
      "name": "Marcellus Lascelles",
      "email": "mlascelles1v@hugedomains.com",
      "password": "gC4'#C1F,e+L7++"
    },
    {
      "id": 69,
      "name": "Agretha Garton",
      "email": "agarton1w@biblegateway.com",
      "password": "kW1+8{y!"
    },
    {
      "id": 70,
      "name": "Sean O'Dee",
      "email": "sodee1x@scribd.com",
      "password": "aU8@S}p,n/!"
    },
    {
      "id": 72,
      "name": "Rodrigo Klimochkin",
      "email": "rklimochkin1z@auda.org.au",
      "password": "qL0)5<x$j2e9kg"
    },
    {
      "id": 73,
      "name": "Flss Serjeantson",
      "email": "fserjeantson20@va.gov",
      "password": "sO0'd+bA1>T"
    },
    {
      "id": 74,
      "name": "Even Surtees",
      "email": "esurtees21@bloomberg.com",
      "password": "bG1(ApI$9Au#{"
    },
    {
      "id": 75,
      "name": "Gaye Dye",
      "email": "gdye22@gmpg.org",
      "password": "jI5}>11ZV"
    },
    {
      "id": 76,
      "name": "Bryna Treske",
      "email": "btreske23@latimes.com",
      "password": "nW9=5@r$)Y"
    },
    {
      "id": 77,
      "name": "Cornela Merman",
      "email": "cmerman24@live.com",
      "password": "zV1>zBeK"
    },
    {
      "id": 78,
      "name": "Ezra Galletly",
      "email": "egalletly25@360.cn",
      "password": "kF3'o7'MQA/G5"
    },
    {
      "id": 79,
      "name": "Doreen Labram",
      "email": "dlabram26@cbc.ca",
      "password": "hR8(EQe9\\Kh\"kVIy"
    },
    {
      "id": 80,
      "name": "Waite Vossing",
      "email": "wvossing27@altervista.org",
      "password": "gW8/`5(Mq?sF7r"
    },
    {
      "id": 81,
      "name": "Zach Grelak",
      "email": "zgrelak28@example.com",
      "password": "gF6#K~q=Sp)"
    },
    {
      "id": 82,
      "name": "Flo Grizard",
      "email": "fgrizard29@t-online.de",
      "password": "cT2*@=6=~.+O`G"
    },
    {
      "id": 83,
      "name": "Franny Thundercliffe",
      "email": "fthundercliffe2a@cisco.com",
      "password": "fH5_@.tH0?B.<w4"
    },
    {
      "id": 84,
      "name": "Raoul Handslip",
      "email": "rhandslip2b@illinois.edu",
      "password": "jD0&W|7O`<\"Lq"
    },
    {
      "id": 85,
      "name": "Grantham Shelp",
      "email": "gshelp2c@nifty.com",
      "password": "nG4>LUcnD=UG(|"
    },
    {
      "id": 86,
      "name": "Wyn Snell",
      "email": "wsnell2d@behance.net",
      "password": "uJ8)*3D.1Hf@6"
    },
    {
      "id": 87,
      "name": "Karisa Sumpton",
      "email": "ksumpton2e@csmonitor.com",
      "password": "aV7<|5IB(,"
    },
    {
      "id": 88,
      "name": "Estella Treacy",
      "email": "etreacy2f@unicef.org",
      "password": "pA6=I*Jd_"
    },
    {
      "id": 89,
      "name": "Jeanelle Farrens",
      "email": "jfarrens2g@twitter.com",
      "password": "zV6'm8*9G"
    },
    {
      "id": 90,
      "name": "Rona Punch",
      "email": "rpunch2h@statcounter.com",
      "password": "nJ8.`jpg*6NrUJo"
    },
    {
      "id": 91,
      "name": "Lalo Ingley",
      "email": "lingley2i@nytimes.com",
      "password": "sF6=2}t_oXD=8&"
    },
    {
      "id": 92,
      "name": "Marika Pyner",
      "email": "mpyner2j@trellian.com",
      "password": "eQ1<OKw4/Hj)3(9l"
    },
    {
      "id": 93,
      "name": "Cal Longmire",
      "email": "clongmire2k@sun.com",
      "password": "uK6\\9}=+"
    },
    {
      "id": 94,
      "name": "Kary Heiton",
      "email": "kheiton2l@wp.com",
      "password": "lM0\"t,~i@NM`z$it"
    },
    {
      "id": 95,
      "name": "Lila Spridgen",
      "email": "lspridgen2m@tumblr.com",
      "password": "fB6.B<oDQRFJ_)"
    },
    {
      "id": 96,
      "name": "Odella Kyle",
      "email": "okyle2n@alibaba.com",
      "password": "lP3@\"\"P%LaT@l/i\\"
    },
    {
      "id": 97,
      "name": "Cassy Schuchmacher",
      "email": "cschuchmacher2o@shutterfly.com",
      "password": "pN8{QC}~sm"
    },
    {
      "id": 98,
      "name": "Harlan Mates",
      "email": "hmates2p@google.nl",
      "password": "lT1|00sb7"
    },
    {
      "id": 99,
      "name": "Cletis Hessay",
      "email": "chessay2q@dion.ne.jp",
      "password": "zH9>>sbqS?L66wwI"
    },
    {
      "id": 100,
      "name": "Lottie Fearne",
      "email": "lfearne2r@friendfeed.com",
      "password": "zX3$zDXZOE"
    },
    {
      "id": 101,
      "name": "Dex Du Barry",
      "email": "ddu2s@businessinsider.com",
      "password": "eL8'iXX{Yv}{9c"
    },
    {
      "id": 102,
      "name": "Jdavie De Paoli",
      "email": "jde2t@rediff.com",
      "password": "sF4.q*X7"
    },
    {
      "id": 103,
      "name": "Maura Sadgrove",
      "email": "msadgrove2u@tiny.cc",
      "password": "pK3?v3.Q+?2+aA"
    },
    {
      "id": 104,
      "name": "Sebastien Napoli",
      "email": "snapoli2v@discuz.net",
      "password": "rO4>vl@N|LTFw=G"
    },
    {
      "id": 105,
      "name": "Cory Birts",
      "email": "cbirts2w@ocn.ne.jp",
      "password": "fO6)\"v7xd/``$"
    },
    {
      "id": 106,
      "name": "Keely MacGown",
      "email": "kmacgown2x@ucoz.ru",
      "password": "dS5&B?Dz0"
    },
    {
      "id": 107,
      "name": "Pattie Effaunt",
      "email": "peffaunt2y@google.ca",
      "password": "sH4&tV>4{rN9"
    },
    {
      "id": 108,
      "name": "Cariotta Barukh",
      "email": "cbarukh2z@toplist.cz",
      "password": "xF0,vfUMwGB8xK*"
    },
    {
      "id": 109,
      "name": "Alexia Rougier",
      "email": "arougier30@last.fm",
      "password": "yY5?u}z{wK"
    },
    {
      "id": 110,
      "name": "Bondy Narey",
      "email": "bnarey31@google.it",
      "password": "xL8|GhO%(4iQSZ\\"
    },
    {
      "id": 111,
      "name": "Beatrix Grouvel",
      "email": "bgrouvel32@sfgate.com",
      "password": "pY0+`b5+\\H6_YNN"
    },
    {
      "id": 112,
      "name": "Bren Carnell",
      "email": "bcarnell33@addtoany.com",
      "password": "sM4$YuIhM"
    },
    {
      "id": 113,
      "name": "Clemmy Jaslem",
      "email": "cjaslem34@opensource.org",
      "password": "gR2!\\)wBVcZ<j"
    },
    {
      "id": 114,
      "name": "Herby Hinchon",
      "email": "hhinchon35@amazon.de",
      "password": "hL1}J!iw$RQ=\""
    },
    {
      "id": 115,
      "name": "Angelina Tapsfield",
      "email": "atapsfield36@patch.com",
      "password": "xV1}VB\"ao!RMFu"
    },
    {
      "id": 116,
      "name": "Maynord Rispen",
      "email": "mrispen37@unc.edu",
      "password": "nR0{u(0Nr)#,e("
    },
    {
      "id": 117,
      "name": "Lorinda Glaister",
      "email": "lglaister38@nature.com",
      "password": "qD1\"O2+=@"
    },
    {
      "id": 118,
      "name": "Brannon Files",
      "email": "bfiles39@wikipedia.org",
      "password": "xW7<2@&b0sWUdwbH"
    },
    {
      "id": 119,
      "name": "Kristine Dirand",
      "email": "kdirand3a@csmonitor.com",
      "password": "mQ8`<xt+}U@V<"
    },
    {
      "id": 120,
      "name": "Darnell Twining",
      "email": "dtwining3b@hao123.com",
      "password": "sY8{aOi+Lg"
    },
    {
      "id": 121,
      "name": "Kimberlyn Goodrich",
      "email": "kgoodrich3c@homestead.com",
      "password": "gM6&u#fFihAa_mKT"
    },
    {
      "id": 122,
      "name": "Portia Feckey",
      "email": "pfeckey3d@jiathis.com",
      "password": "oG5$+b._wv5{"
    },
    {
      "id": 123,
      "name": "June Boldock",
      "email": "jboldock3e@vk.com",
      "password": "bC1*=kqPvmv"
    },
    {
      "id": 124,
      "name": "Arte Goldis",
      "email": "agoldis3f@japanpost.jp",
      "password": "zC7<tT\\6Sy<3PLe_"
    },
    {
      "id": 125,
      "name": "Jaquelyn Chisholme",
      "email": "jchisholme3g@acquirethisname.com",
      "password": "aJ5#xnf+>Ct2M"
    },
    {
      "id": 126,
      "name": "Sherwood Duchatel",
      "email": "sduchatel3h@google.it",
      "password": "zM1\"N!!t"
    },
    {
      "id": 127,
      "name": "Stanwood Aldins",
      "email": "saldins3i@illinois.edu",
      "password": "bB9|!?4<h3%V"
    },
    {
      "id": 128,
      "name": "Brande Cullon",
      "email": "bcullon3j@bigcartel.com",
      "password": "kE4|)1e8!pv"
    },
    {
      "id": 129,
      "name": "Bail Himpson",
      "email": "bhimpson3k@mozilla.com",
      "password": "pN6>`2RthC5"
    },
    {
      "id": 130,
      "name": "Verla Fulkes",
      "email": "vfulkes3l@pinterest.com",
      "password": "tZ6>He6XqWU/Z,2"
    },
    {
      "id": 131,
      "name": "Flor Croan",
      "email": "fcroan3m@usda.gov",
      "password": "nB6!Yo)2w\"Ws>"
    },
    {
      "id": 132,
      "name": "Izzy Kagan",
      "email": "ikagan3n@example.com",
      "password": "nT4+=>*O}_+Pz+k"
    },
    {
      "id": 133,
      "name": "Jenine Marlon",
      "email": "jmarlon3o@tinyurl.com",
      "password": "wE5~J`g(!5gW2@0a"
    },
    {
      "id": 134,
      "name": "Bunni Josipovitz",
      "email": "bjosipovitz3p@newsvine.com",
      "password": "nP9\\bC21/w4"
    },
    {
      "id": 135,
      "name": "Millard Henken",
      "email": "mhenken3q@taobao.com",
      "password": "aK0'hqNxMZq1&W_"
    },
    {
      "id": 136,
      "name": "Reinold Pawlik",
      "email": "rpawlik3r@dion.ne.jp",
      "password": "cZ2\"Ukg?@a%F%%~n"
    },
    {
      "id": 137,
      "name": "Elroy Borgnol",
      "email": "eborgnol3s@storify.com",
      "password": "kN8'=t)yQ*>"
    },
    {
      "id": 138,
      "name": "Kendre Kleinsmuntz",
      "email": "kkleinsmuntz3t@hhs.gov",
      "password": "rB0_28!n$Vy!U$y"
    },
    {
      "id": 139,
      "name": "Veronike Hales",
      "email": "vhales3u@bloomberg.com",
      "password": "iW6?nDUPUH7"
    },
    {
      "id": 140,
      "name": "Merry Baddeley",
      "email": "mbaddeley3v@fc2.com",
      "password": "pY8=!Q@{s<_6v"
    },
    {
      "id": 141,
      "name": "Sukey Birney",
      "email": "sbirney3w@wiley.com",
      "password": "wK9#JA'P$w*"
    },
    {
      "id": 142,
      "name": "Nadeen Gotcliffe",
      "email": "ngotcliffe3x@latimes.com",
      "password": "iF8)gF)e,9hYC"
    },
    {
      "id": 143,
      "name": "Kinnie Bewlay",
      "email": "kbewlay3y@taobao.com",
      "password": "aB0,#_N#IPCKyNw,"
    },
    {
      "id": 144,
      "name": "Reggy Gilardengo",
      "email": "rgilardengo3z@dyndns.org",
      "password": "fZ1\\1n7I=q`d%"
    },
    {
      "id": 145,
      "name": "Inglebert Ferson",
      "email": "iferson40@ca.gov",
      "password": "xD6}vXt`0c=,#r"
    },
    {
      "id": 146,
      "name": "Farrell Lowers",
      "email": "flowers41@alibaba.com",
      "password": "pC1`c0d3"
    },
    {
      "id": 147,
      "name": "Cody Sucre",
      "email": "csucre42@businessweek.com",
      "password": "xX9.ifs>t\\"
    },
    {
      "id": 148,
      "name": "Charlean Antat",
      "email": "cantat43@blogs.com",
      "password": "tW4&nyK}\"Ib?~x"
    },
    {
      "id": 149,
      "name": "Marline Colquyte",
      "email": "mcolquyte44@furl.net",
      "password": "bH6%cXQsa"
    },
    {
      "id": 150,
      "name": "Haydon Trittam",
      "email": "htrittam45@statcounter.com",
      "password": "oN1<5,!f0Rn`od\"="
    },
    {
      "id": 151,
      "name": "Enrika Byneth",
      "email": "ebyneth46@woothemes.com",
      "password": "gN2._{Rbf#*oB"
    },
    {
      "id": 152,
      "name": "Zsa zsa Sedwick",
      "email": "zzsa47@creativecommons.org",
      "password": "nS5\\3#.iLzI%V"
    },
    {
      "id": 153,
      "name": "Wolfy Ridehalgh",
      "email": "wridehalgh48@opera.com",
      "password": "bK3~c@n6"
    },
    {
      "id": 154,
      "name": "Mortie Livett",
      "email": "mlivett49@google.nl",
      "password": "iH4!)JqrT@"
    },
    {
      "id": 155,
      "name": "Mikael Paulsen",
      "email": "mpaulsen4a@odnoklassniki.ru",
      "password": "aK0\"jf'maY~3RS"
    },
    {
      "id": 156,
      "name": "Dita Altoft",
      "email": "daltoft4b@mac.com",
      "password": "wZ5#AJgtiP1@4\\ws"
    },
    {
      "id": 157,
      "name": "Georgi Lyttle",
      "email": "glyttle4c@posterous.com",
      "password": "zF5><<IyL(SY8"
    },
    {
      "id": 158,
      "name": "Arch BURWIN",
      "email": "aburwin4d@cnet.com",
      "password": "nP6\\Z'=!cNU0O"
    },
    {
      "id": 159,
      "name": "Ode Nan Carrow",
      "email": "onan4e@umn.edu",
      "password": "bM0&7Y.=+"
    },
    {
      "id": 160,
      "name": "Ebony McCawley",
      "email": "emccawley4f@hibu.com",
      "password": "yM4/,bABz0"
    },
    {
      "id": 161,
      "name": "Kelley Borley",
      "email": "kborley4g@twitpic.com",
      "password": "dK0)_cq!K$bMk"
    },
    {
      "id": 162,
      "name": "Harald Morl",
      "email": "hmorl4h@timesonline.co.uk",
      "password": "fD3$20&8bGnN1?5"
    },
    {
      "id": 163,
      "name": "Cristy Patel",
      "email": "cpatel4i@g.co",
      "password": "fJ9)+O8d"
    },
    {
      "id": 164,
      "name": "Rubi Knowller",
      "email": "rknowller4j@squarespace.com",
      "password": "jA7\"@<GJ$~}"
    },
    {
      "id": 165,
      "name": "Shem Pearmain",
      "email": "spearmain4k@ucoz.ru",
      "password": "aC4\"r\\cb}(*w\"Uo"
    },
    {
      "id": 166,
      "name": "Lorenza Levicount",
      "email": "llevicount4l@prweb.com",
      "password": "rB6{M1w1D,9vEmG"
    },
    {
      "id": 167,
      "name": "Ashli Sloegrave",
      "email": "asloegrave4m@histats.com",
      "password": "rJ0{=`iz=.&k"
    },
    {
      "id": 168,
      "name": "Heinrick McIlwaine",
      "email": "hmcilwaine4n@domainmarket.com",
      "password": "rQ6{'FD)c1Axu"
    },
    {
      "id": 169,
      "name": "Thaddeus Arbuckel",
      "email": "tarbuckel4o@netscape.com",
      "password": "hT5,`SHiVu"
    },
    {
      "id": 170,
      "name": "Prince Helgass",
      "email": "phelgass4p@hugedomains.com",
      "password": "dC0%'/V8$i@QrkI"
    },
    {
      "id": 171,
      "name": "Holmes Goude",
      "email": "hgoude4q@chron.com",
      "password": "eQ7%RB!7f0?KOg*"
    },
    {
      "id": 172,
      "name": "Ingeberg McDugal",
      "email": "imcdugal4r@liveinternet.ru",
      "password": "nZ6${uXO%KxS<"
    },
    {
      "id": 173,
      "name": "Alys Schoroder",
      "email": "aschoroder4s@bigcartel.com",
      "password": "iE9>D(T74l|F"
    },
    {
      "id": 174,
      "name": "Udall Skittrall",
      "email": "uskittrall4t@creativecommons.org",
      "password": "lJ1$i8P)1/(kR*i_"
    },
    {
      "id": 175,
      "name": "Ariela Gonning",
      "email": "agonning4u@umn.edu",
      "password": "bT1_ux&3+@9J>'"
    },
    {
      "id": 176,
      "name": "Connie McMurdo",
      "email": "cmcmurdo4v@google.nl",
      "password": "cI9,fd=~WNNmN>ni"
    },
    {
      "id": 177,
      "name": "Vance Igonet",
      "email": "vigonet4w@barnesandnoble.com",
      "password": "iE0`W1d+=8{RyFbH"
    },
    {
      "id": 178,
      "name": "Sampson Gonneau",
      "email": "sgonneau4x@nasa.gov",
      "password": "gM5@zhDJB"
    },
    {
      "id": 179,
      "name": "Birdie Tarren",
      "email": "btarren4y@zimbio.com",
      "password": "eV0*CES|Dy\\/jbE1"
    },
    {
      "id": 180,
      "name": "Aland Filippozzi",
      "email": "afilippozzi4z@spotify.com",
      "password": "zV4})F(r06j~w,"
    },
    {
      "id": 181,
      "name": "Temp Hardson",
      "email": "thardson50@surveymonkey.com",
      "password": "cJ7<%,3!1"
    },
    {
      "id": 182,
      "name": "Lesley Krysztowczyk",
      "email": "lkrysztowczyk51@wikipedia.org",
      "password": "aX5~xSq97"
    },
    {
      "id": 183,
      "name": "Darcy Garioch",
      "email": "dgarioch52@deliciousdays.com",
      "password": "oK2#Iu'ySP546kz"
    },
    {
      "id": 184,
      "name": "Celina Procter",
      "email": "cprocter53@umn.edu",
      "password": "vW8\"Q5m#W2gcw"
    },
    {
      "id": 185,
      "name": "Jocelin Olver",
      "email": "jolver54@lulu.com",
      "password": "mT6$/JjVp"
    },
    {
      "id": 186,
      "name": "Kalvin Sweetnam",
      "email": "ksweetnam55@myspace.com",
      "password": "rZ1'f2.y"
    },
    {
      "id": 187,
      "name": "Engracia Catcheside",
      "email": "ecatcheside56@wikispaces.com",
      "password": "dU2@0WKU(K8<CJ=`"
    },
    {
      "id": 188,
      "name": "Emogene Notti",
      "email": "enotti57@squidoo.com",
      "password": "pZ0<!S%}9XsN"
    },
    {
      "id": 189,
      "name": "Nedi Rabbitt",
      "email": "nrabbitt58@shop-pro.jp",
      "password": "fU1(!%f2E,k"
    },
    {
      "id": 190,
      "name": "Junie Lutas",
      "email": "jlutas59@gizmodo.com",
      "password": "kR1~Pqet"
    },
    {
      "id": 191,
      "name": "Catie Budnik",
      "email": "cbudnik5a@1688.com",
      "password": "gK5\"HkD.n1d?"
    },
    {
      "id": 192,
      "name": "Hester Brett",
      "email": "hbrett5b@kickstarter.com",
      "password": "uX6|FAu<>9e_8Z"
    },
    {
      "id": 193,
      "name": "Beau Nice",
      "email": "bnice5c@usnews.com",
      "password": "uA7>b`=*"
    },
    {
      "id": 194,
      "name": "Hilliard Duigan",
      "email": "hduigan5d@about.com",
      "password": "bL8,\\4d*QUc/S~"
    },
    {
      "id": 195,
      "name": "Neal Chittie",
      "email": "nchittie5e@bing.com",
      "password": "lD7.Y`R`>{j3mC"
    },
    {
      "id": 196,
      "name": "Margi Boynton",
      "email": "mboynton5f@jimdo.com",
      "password": "yU1>\\<6jpF?e3MK7"
    },
    {
      "id": 197,
      "name": "Sadella Issett",
      "email": "sissett5g@multiply.com",
      "password": "xD8|q|`3qC{J,"
    },
    {
      "id": 198,
      "name": "Pammy Craney",
      "email": "pcraney5h@cisco.com",
      "password": "mH6/@HS/>"
    },
    {
      "id": 199,
      "name": "Sylas Roscow",
      "email": "sroscow5i@homestead.com",
      "password": "pC9~\"dzZ&K,>$Ly."
    },
    {
      "id": 200,
      "name": "Artair Barnby",
      "email": "abarnby5j@foxnews.com",
      "password": "zM3?9FU3"
    },
    {
      "id": 201,
      "name": "Aurora McDougle",
      "email": "amcdougle5k@hp.com",
      "password": "nY0!GG!(U(K,"
    },
    {
      "id": 202,
      "name": "Cloe Bickers",
      "email": "cbickers5l@google.it",
      "password": "eG8#\\*aRNALz2P"
    },
    {
      "id": 203,
      "name": "Miltie Halpin",
      "email": "mhalpin5m@hc360.com",
      "password": "gP5>Dy$3FC2'IHi@"
    },
    {
      "id": 204,
      "name": "Selene Dorber",
      "email": "sdorber5n@e-recht24.de",
      "password": "sQ8\\X\"wOY"
    },
    {
      "id": 205,
      "name": "Mariele Elliff",
      "email": "melliff5o@smugmug.com",
      "password": "kL1%&Lst/tz"
    },
    {
      "id": 206,
      "name": "Erena Craddy",
      "email": "ecraddy5p@kickstarter.com",
      "password": "nA8{9d+mBM~!"
    },
    {
      "id": 207,
      "name": "Violetta Weiss",
      "email": "vweiss5q@vimeo.com",
      "password": "gW6~zwWZ%#\\zPo8O"
    },
    {
      "id": 208,
      "name": "Ancell Frye",
      "email": "afrye5r@i2i.jp",
      "password": "fE3\"RV9Sk"
    },
    {
      "id": 209,
      "name": "Tull Celloni",
      "email": "tcelloni5s@admin.ch",
      "password": "cS2(}LZ\"#"
    },
    {
      "id": 210,
      "name": "Chanda Collecott",
      "email": "ccollecott5t@studiopress.com",
      "password": "nF6/Le%UJoks"
    },
    {
      "id": 211,
      "name": "Claybourne MacAllaster",
      "email": "cmacallaster5u@uiuc.edu",
      "password": "fW1&_hdNT6d"
    },
    {
      "id": 212,
      "name": "Helenelizabeth Howat",
      "email": "hhowat5v@yellowbook.com",
      "password": "gT7|o+vY&x~ehD"
    },
    {
      "id": 213,
      "name": "Corine Bagge",
      "email": "cbagge5w@patch.com",
      "password": "sG5$Yx.uOTkbR'g"
    },
    {
      "id": 214,
      "name": "Trip Gratland",
      "email": "tgratland5x@ftc.gov",
      "password": "gF6\"18@X9Yawr"
    },
    {
      "id": 215,
      "name": "Jewell Lenin",
      "email": "jlenin5y@imgur.com",
      "password": "uU3'}Uo$*"
    },
    {
      "id": 216,
      "name": "Byran Kings",
      "email": "bkings5z@businessinsider.com",
      "password": "jP4?Gf9L&CzrL"
    },
    {
      "id": 217,
      "name": "Rivkah Samme",
      "email": "rsamme60@plala.or.jp",
      "password": "gC9\\q\\!+T\"/&h#"
    },
    {
      "id": 218,
      "name": "Norean Brakespear",
      "email": "nbrakespear61@marketwatch.com",
      "password": "yA1/1FT\\+g#k\\j#n"
    },
    {
      "id": 219,
      "name": "Zilvia Twomey",
      "email": "ztwomey62@tinypic.com",
      "password": "uZ8(?W>~gYwQ=~"
    },
    {
      "id": 220,
      "name": "Worthington Wilsee",
      "email": "wwilsee63@japanpost.jp",
      "password": "kO8*ee|dsR+noX"
    },
    {
      "id": 221,
      "name": "Marylin Kollatsch",
      "email": "mkollatsch64@printfriendly.com",
      "password": "xS3.g%<'QO"
    },
    {
      "id": 222,
      "name": "Carry Buzzing",
      "email": "cbuzzing65@cnet.com",
      "password": "uM4/z=sFAsV%WY\\t"
    },
    {
      "id": 223,
      "name": "Joey Fieldgate",
      "email": "jfieldgate66@networkadvertising.org",
      "password": "mC1,%)},?"
    },
    {
      "id": 224,
      "name": "Emmye Kingswood",
      "email": "ekingswood67@technorati.com",
      "password": "xY7`?0C6*)X"
    },
    {
      "id": 225,
      "name": "Bernice Geach",
      "email": "bgeach68@linkedin.com",
      "password": "oJ5}uiPpG<>8"
    },
    {
      "id": 226,
      "name": "Erinn Gerald",
      "email": "egerald69@unblog.fr",
      "password": "yX6!&2,,SB#d}P"
    },
    {
      "id": 227,
      "name": "Francesco Woloschinski",
      "email": "fwoloschinski6a@cnbc.com",
      "password": "lE9*WxaXGmhX~%U"
    },
    {
      "id": 228,
      "name": "Ennis Olczak",
      "email": "eolczak6b@indiegogo.com",
      "password": "rA3.JA4`Nf"
    },
    {
      "id": 229,
      "name": "Carine Dilland",
      "email": "cdilland6c@miitbeian.gov.cn",
      "password": "pI9@}$ayI@Bz"
    },
    {
      "id": 230,
      "name": "Fleur Tabourier",
      "email": "ftabourier6d@opera.com",
      "password": "gP8)Azx}P(8Zy?o"
    },
    {
      "id": 231,
      "name": "Dall Walduck",
      "email": "dwalduck6e@prnewswire.com",
      "password": "pT7}nH*_`Ew&|QTg"
    },
    {
      "id": 232,
      "name": "Eydie Dobbing",
      "email": "edobbing6f@cocolog-nifty.com",
      "password": "tZ4?D{Hly)gS"
    },
    {
      "id": 233,
      "name": "Benjy Fagence",
      "email": "bfagence6g@csmonitor.com",
      "password": "wH6`EXoqYu*ZWOTb"
    },
    {
      "id": 234,
      "name": "Beverlie Trevaskiss",
      "email": "btrevaskiss6h@mozilla.org",
      "password": "vU1#wg!Fck"
    },
    {
      "id": 235,
      "name": "Johann Matusson",
      "email": "jmatusson6i@cbc.ca",
      "password": "lD7,>WOKvG"
    },
    {
      "id": 236,
      "name": "Zuzana Mathewes",
      "email": "zmathewes6j@census.gov",
      "password": "qJ2/0T~BTozJJa6"
    },
    {
      "id": 237,
      "name": "Gabriela Wipper",
      "email": "gwipper6k@ovh.net",
      "password": "iR4'JGL}}E%"
    },
    {
      "id": 238,
      "name": "Daniel Trowl",
      "email": "dtrowl6l@purevolume.com",
      "password": "tK1(\"vfY"
    },
    {
      "id": 239,
      "name": "Bevan Hans",
      "email": "bhans6m@webs.com",
      "password": "vN2$An6#W<{"
    },
    {
      "id": 240,
      "name": "Christos Sonner",
      "email": "csonner6n@bizjournals.com",
      "password": "eH4>5RmBJ"
    },
    {
      "id": 241,
      "name": "Averyl Ferro",
      "email": "aferro6o@illinois.edu",
      "password": "fE7>fpeE"
    },
    {
      "id": 242,
      "name": "Ilario Issacov",
      "email": "iissacov6p@sogou.com",
      "password": "fC7%y9c.|1"
    },
    {
      "id": 243,
      "name": "Winifield Calderonello",
      "email": "wcalderonello6q@sina.com.cn",
      "password": "sD0$FyGsnb"
    },
    {
      "id": 244,
      "name": "Freeland Thackray",
      "email": "fthackray6r@toplist.cz",
      "password": "cP8\"c)/yC@C_*"
    },
    {
      "id": 245,
      "name": "Baudoin Sandford",
      "email": "bsandford6s@telegraph.co.uk",
      "password": "dL2.5qH`g"
    },
    {
      "id": 246,
      "name": "Llewellyn Faich",
      "email": "lfaich6t@mayoclinic.com",
      "password": "jZ9!znDh}|@\\'N"
    },
    {
      "id": 247,
      "name": "Kippar Wynett",
      "email": "kwynett6u@goodreads.com",
      "password": "aO8(*Rl7"
    },
    {
      "id": 248,
      "name": "Janella Stuckford",
      "email": "jstuckford6v@cloudflare.com",
      "password": "tA3>%3lX8~H*bS+F"
    },
    {
      "id": 249,
      "name": "Muriel Ruddle",
      "email": "mruddle6w@thetimes.co.uk",
      "password": "oB9\"'z<yO"
    },
    {
      "id": 250,
      "name": "Sayer Pohlke",
      "email": "spohlke6x@trellian.com",
      "password": "nP8%nhn=Zc4"
    },
    {
      "name": "Matt Sullivan",
      "email": "matt@abc.com",
      "password": "fhdfdfsf",
      "id": 251
    },
    {
      "name": "Henry Lamb",
      "email": "henry@abc.com",
      "password": "hspgnejn",
      "id": 252
    },
    {
      "name": "Cassandry Pinn",
      "email": "cpinney7@bbb.or",
      "password": "dsmwfmlds",
      "id": 253
    },
    {
      "name": "Mike Johnsons",
      "email": "mikej@abc.com",
      "password": "mddfhs876f",
      "id": 254
    }
  ]
}